json_parser/__init__.py
json_parser/json_parser.py
json_parser/lexer.py
json_parser/parser.py
json_parser/test_runner.py
json_parser_cli-0.1.2.dist-info/METADATA
json_parser_cli-0.1.2.dist-info/WHEEL
json_parser_cli-0.1.2.dist-info/entry_points.txt
json_parser_cli-0.1.2.dist-info/licenses/LICENSE.md
json_parser_cli-0.1.2.dist-info/RECORD
