Metadata-Version: 2.4
Name: json-parser-cli
Version: 0.1.2
Summary: A JSON parser CLI tool
Project-URL: Repository, https://github.com/Anand-0037/json-parser
Author-email: Anand Vashishtha <anandcollege07@gmail.com>
License: MIT
License-File: LICENSE.md
Keywords: cli,compiler,json,lexer,parser
Classifier: Development Status :: 3 - Alpha
Classifier: Intended Audience :: Developers
Classifier: License :: OSI Approved :: MIT License
Classifier: Programming Language :: Python :: 3
Classifier: Programming Language :: Python :: 3.11
Requires-Python: >=3.11
